package com.tencent.open.cgireport;

import android.content.Context;
import android.os.Bundle;

class d extends Thread
{
  d(ReportManager paramReportManager, String paramString, Context paramContext, Bundle paramBundle)
  {
  }

  // ERROR //
  public void run()
  {
    // Byte code:
    //   0: ldc 34
    //   2: new 36	java/lang/StringBuilder
    //   5: dup
    //   6: invokespecial 37	java/lang/StringBuilder:<init>	()V
    //   9: ldc 39
    //   11: invokevirtual 43	java/lang/StringBuilder:append	(Ljava/lang/String;)Ljava/lang/StringBuilder;
    //   14: aload_0
    //   15: getfield 18	com/tencent/open/cgireport/d:a	Ljava/lang/String;
    //   18: invokevirtual 43	java/lang/StringBuilder:append	(Ljava/lang/String;)Ljava/lang/StringBuilder;
    //   21: invokevirtual 47	java/lang/StringBuilder:toString	()Ljava/lang/String;
    //   24: invokestatic 53	android/util/Log:i	(Ljava/lang/String;Ljava/lang/String;)I
    //   27: pop
    //   28: aload_0
    //   29: getfield 16	com/tencent/open/cgireport/d:d	Lcom/tencent/open/cgireport/ReportManager;
    //   32: aload_0
    //   33: getfield 20	com/tencent/open/cgireport/d:b	Landroid/content/Context;
    //   36: aconst_null
    //   37: invokestatic 58	com/tencent/common/OpenConfig:a	(Landroid/content/Context;Ljava/lang/String;)Lcom/tencent/common/OpenConfig;
    //   40: ldc 60
    //   42: invokevirtual 63	com/tencent/common/OpenConfig:b	(Ljava/lang/String;)I
    //   45: invokestatic 69	com/tencent/open/cgireport/ReportManager:access$002	(Lcom/tencent/open/cgireport/ReportManager;I)I
    //   48: pop
    //   49: aload_0
    //   50: getfield 16	com/tencent/open/cgireport/d:d	Lcom/tencent/open/cgireport/ReportManager;
    //   53: astore_3
    //   54: aload_0
    //   55: getfield 16	com/tencent/open/cgireport/d:d	Lcom/tencent/open/cgireport/ReportManager;
    //   58: invokestatic 73	com/tencent/open/cgireport/ReportManager:access$000	(Lcom/tencent/open/cgireport/ReportManager;)I
    //   61: ifne +200 -> 261
    //   64: iconst_3
    //   65: istore 4
    //   67: aload_3
    //   68: iload 4
    //   70: invokestatic 69	com/tencent/open/cgireport/ReportManager:access$002	(Lcom/tencent/open/cgireport/ReportManager;I)I
    //   73: pop
    //   74: iconst_0
    //   75: istore 6
    //   77: iconst_0
    //   78: istore 7
    //   80: iinc 7 1
    //   83: ldc 34
    //   85: new 36	java/lang/StringBuilder
    //   88: dup
    //   89: invokespecial 37	java/lang/StringBuilder:<init>	()V
    //   92: ldc 75
    //   94: invokevirtual 43	java/lang/StringBuilder:append	(Ljava/lang/String;)Ljava/lang/StringBuilder;
    //   97: iload 7
    //   99: invokevirtual 78	java/lang/StringBuilder:append	(I)Ljava/lang/StringBuilder;
    //   102: invokevirtual 47	java/lang/StringBuilder:toString	()Ljava/lang/String;
    //   105: invokestatic 53	android/util/Log:i	(Ljava/lang/String;Ljava/lang/String;)I
    //   108: pop
    //   109: aload_0
    //   110: getfield 20	com/tencent/open/cgireport/d:b	Landroid/content/Context;
    //   113: aconst_null
    //   114: aload_0
    //   115: getfield 18	com/tencent/open/cgireport/d:a	Ljava/lang/String;
    //   118: invokestatic 84	com/tencent/sdkutil/HttpUtils:getHttpClient	(Landroid/content/Context;Ljava/lang/String;Ljava/lang/String;)Lorg/apache/http/client/HttpClient;
    //   121: astore 19
    //   123: new 86	org/apache/http/client/methods/HttpPost
    //   126: dup
    //   127: aload_0
    //   128: getfield 18	com/tencent/open/cgireport/d:a	Ljava/lang/String;
    //   131: invokespecial 89	org/apache/http/client/methods/HttpPost:<init>	(Ljava/lang/String;)V
    //   134: astore 20
    //   136: aload 20
    //   138: ldc 91
    //   140: ldc 93
    //   142: invokevirtual 97	org/apache/http/client/methods/HttpPost:addHeader	(Ljava/lang/String;Ljava/lang/String;)V
    //   145: aload 20
    //   147: ldc 99
    //   149: ldc 101
    //   151: invokevirtual 104	org/apache/http/client/methods/HttpPost:setHeader	(Ljava/lang/String;Ljava/lang/String;)V
    //   154: aload 20
    //   156: new 106	org/apache/http/entity/ByteArrayEntity
    //   159: dup
    //   160: aload_0
    //   161: getfield 22	com/tencent/open/cgireport/d:c	Landroid/os/Bundle;
    //   164: invokestatic 112	com/tencent/sdkutil/Util:encodeUrl	(Landroid/os/Bundle;)Ljava/lang/String;
    //   167: invokevirtual 118	java/lang/String:getBytes	()[B
    //   170: invokespecial 121	org/apache/http/entity/ByteArrayEntity:<init>	([B)V
    //   173: invokevirtual 125	org/apache/http/client/methods/HttpPost:setEntity	(Lorg/apache/http/HttpEntity;)V
    //   176: aload 19
    //   178: aload 20
    //   180: invokeinterface 131 2 0
    //   185: invokeinterface 137 1 0
    //   190: invokeinterface 143 1 0
    //   195: sipush 200
    //   198: if_icmpeq +75 -> 273
    //   201: ldc 34
    //   203: ldc 145
    //   205: invokestatic 148	android/util/Log:e	(Ljava/lang/String;Ljava/lang/String;)I
    //   208: pop
    //   209: aload_0
    //   210: getfield 16	com/tencent/open/cgireport/d:d	Lcom/tencent/open/cgireport/ReportManager;
    //   213: iconst_0
    //   214: invokestatic 152	com/tencent/open/cgireport/ReportManager:access$102	(Lcom/tencent/open/cgireport/ReportManager;Z)Z
    //   217: pop
    //   218: ldc 34
    //   220: new 36	java/lang/StringBuilder
    //   223: dup
    //   224: invokespecial 37	java/lang/StringBuilder:<init>	()V
    //   227: ldc 154
    //   229: invokevirtual 43	java/lang/StringBuilder:append	(Ljava/lang/String;)Ljava/lang/StringBuilder;
    //   232: aload_0
    //   233: getfield 18	com/tencent/open/cgireport/d:a	Ljava/lang/String;
    //   236: invokevirtual 43	java/lang/StringBuilder:append	(Ljava/lang/String;)Ljava/lang/StringBuilder;
    //   239: invokevirtual 47	java/lang/StringBuilder:toString	()Ljava/lang/String;
    //   242: invokestatic 53	android/util/Log:i	(Ljava/lang/String;Ljava/lang/String;)I
    //   245: pop
    //   246: iload 6
    //   248: iconst_1
    //   249: if_icmpne +96 -> 345
    //   252: ldc 34
    //   254: ldc 156
    //   256: invokestatic 53	android/util/Log:i	(Ljava/lang/String;Ljava/lang/String;)I
    //   259: pop
    //   260: return
    //   261: aload_0
    //   262: getfield 16	com/tencent/open/cgireport/d:d	Lcom/tencent/open/cgireport/ReportManager;
    //   265: invokestatic 73	com/tencent/open/cgireport/ReportManager:access$000	(Lcom/tencent/open/cgireport/ReportManager;)I
    //   268: istore 4
    //   270: goto -203 -> 67
    //   273: ldc 34
    //   275: ldc 158
    //   277: invokestatic 53	android/util/Log:i	(Ljava/lang/String;Ljava/lang/String;)I
    //   280: pop
    //   281: iconst_1
    //   282: istore 6
    //   284: goto -75 -> 209
    //   287: astore 17
    //   289: aload 17
    //   291: invokevirtual 161	org/apache/http/conn/ConnectTimeoutException:printStackTrace	()V
    //   294: ldc 34
    //   296: ldc 163
    //   298: invokestatic 148	android/util/Log:e	(Ljava/lang/String;Ljava/lang/String;)I
    //   301: pop
    //   302: iload 7
    //   304: aload_0
    //   305: getfield 16	com/tencent/open/cgireport/d:d	Lcom/tencent/open/cgireport/ReportManager;
    //   308: invokestatic 73	com/tencent/open/cgireport/ReportManager:access$000	(Lcom/tencent/open/cgireport/ReportManager;)I
    //   311: if_icmplt -231 -> 80
    //   314: goto -105 -> 209
    //   317: astore 16
    //   319: aload 16
    //   321: invokevirtual 164	java/net/SocketTimeoutException:printStackTrace	()V
    //   324: goto -22 -> 302
    //   327: astore 9
    //   329: aload 9
    //   331: invokevirtual 165	java/lang/Exception:printStackTrace	()V
    //   334: ldc 34
    //   336: ldc 167
    //   338: invokestatic 148	android/util/Log:e	(Ljava/lang/String;Ljava/lang/String;)I
    //   341: pop
    //   342: goto -133 -> 209
    //   345: ldc 34
    //   347: ldc 169
    //   349: invokestatic 148	android/util/Log:e	(Ljava/lang/String;Ljava/lang/String;)I
    //   352: pop
    //   353: aload_0
    //   354: getfield 16	com/tencent/open/cgireport/d:d	Lcom/tencent/open/cgireport/ReportManager;
    //   357: invokestatic 173	com/tencent/open/cgireport/ReportManager:access$300	(Lcom/tencent/open/cgireport/ReportManager;)Lcom/tencent/open/cgireport/e;
    //   360: aload_0
    //   361: getfield 16	com/tencent/open/cgireport/d:d	Lcom/tencent/open/cgireport/ReportManager;
    //   364: invokestatic 177	com/tencent/open/cgireport/ReportManager:access$200	(Lcom/tencent/open/cgireport/ReportManager;)Ljava/util/ArrayList;
    //   367: invokevirtual 182	com/tencent/open/cgireport/e:a	(Ljava/util/ArrayList;)I
    //   370: pop
    //   371: return
    //   372: astore 23
    //   374: aload 23
    //   376: astore 9
    //   378: iconst_1
    //   379: istore 6
    //   381: goto -52 -> 329
    //   384: astore 22
    //   386: aload 22
    //   388: astore 16
    //   390: iconst_1
    //   391: istore 6
    //   393: goto -74 -> 319
    //   396: astore 21
    //   398: aload 21
    //   400: astore 17
    //   402: iconst_1
    //   403: istore 6
    //   405: goto -116 -> 289
    //
    // Exception table:
    //   from	to	target	type
    //   109	209	287	org/apache/http/conn/ConnectTimeoutException
    //   109	209	317	java/net/SocketTimeoutException
    //   109	209	327	java/lang/Exception
    //   273	281	372	java/lang/Exception
    //   273	281	384	java/net/SocketTimeoutException
    //   273	281	396	org/apache/http/conn/ConnectTimeoutException
  }
}

/* Location:           C:\9exce\android\pj\kaixin_android_3.9.9_034_kaixin001\classes_dex2jar.jar
 * Qualified Name:     com.tencent.open.cgireport.d
 * JD-Core Version:    0.6.0
 */