package com.tencent.tauth;

class DownloadFileFromWeiyun$3 extends Thread
{
  // ERROR //
  public void run()
  {
    // Byte code:
    //   0: new 22	org/apache/http/params/BasicHttpParams
    //   3: dup
    //   4: invokespecial 23	org/apache/http/params/BasicHttpParams:<init>	()V
    //   7: astore_1
    //   8: aload_1
    //   9: sipush 15000
    //   12: invokestatic 29	org/apache/http/params/HttpConnectionParams:setConnectionTimeout	(Lorg/apache/http/params/HttpParams;I)V
    //   15: aload_1
    //   16: sipush 20000
    //   19: invokestatic 32	org/apache/http/params/HttpConnectionParams:setSoTimeout	(Lorg/apache/http/params/HttpParams;I)V
    //   22: aload_1
    //   23: getstatic 38	org/apache/http/HttpVersion:HTTP_1_1	Lorg/apache/http/HttpVersion;
    //   26: invokestatic 44	org/apache/http/params/HttpProtocolParams:setVersion	(Lorg/apache/http/params/HttpParams;Lorg/apache/http/ProtocolVersion;)V
    //   29: aload_1
    //   30: ldc 46
    //   32: invokestatic 50	org/apache/http/params/HttpProtocolParams:setContentCharset	(Lorg/apache/http/params/HttpParams;Ljava/lang/String;)V
    //   35: aload_1
    //   36: ldc 52
    //   38: invokestatic 55	org/apache/http/params/HttpProtocolParams:setUserAgent	(Lorg/apache/http/params/HttpParams;Ljava/lang/String;)V
    //   41: new 57	java/lang/StringBuilder
    //   44: dup
    //   45: invokespecial 58	java/lang/StringBuilder:<init>	()V
    //   48: ldc 60
    //   50: invokevirtual 64	java/lang/StringBuilder:append	(Ljava/lang/String;)Ljava/lang/StringBuilder;
    //   53: aload_0
    //   54: getfield 10	com/tencent/tauth/DownloadFileFromWeiyun$3:this$0	Lcom/tencent/tauth/DownloadFileFromWeiyun;
    //   57: invokestatic 70	com/tencent/tauth/DownloadFileFromWeiyun:access$500	(Lcom/tencent/tauth/DownloadFileFromWeiyun;)Ljava/lang/String;
    //   60: invokevirtual 64	java/lang/StringBuilder:append	(Ljava/lang/String;)Ljava/lang/StringBuilder;
    //   63: ldc 72
    //   65: invokevirtual 64	java/lang/StringBuilder:append	(Ljava/lang/String;)Ljava/lang/StringBuilder;
    //   68: aload_0
    //   69: getfield 10	com/tencent/tauth/DownloadFileFromWeiyun$3:this$0	Lcom/tencent/tauth/DownloadFileFromWeiyun;
    //   72: invokestatic 76	com/tencent/tauth/DownloadFileFromWeiyun:access$400	(Lcom/tencent/tauth/DownloadFileFromWeiyun;)I
    //   75: invokevirtual 79	java/lang/StringBuilder:append	(I)Ljava/lang/StringBuilder;
    //   78: ldc 81
    //   80: invokevirtual 64	java/lang/StringBuilder:append	(Ljava/lang/String;)Ljava/lang/StringBuilder;
    //   83: aload_0
    //   84: getfield 10	com/tencent/tauth/DownloadFileFromWeiyun$3:this$0	Lcom/tencent/tauth/DownloadFileFromWeiyun;
    //   87: invokestatic 84	com/tencent/tauth/DownloadFileFromWeiyun:access$100	(Lcom/tencent/tauth/DownloadFileFromWeiyun;)Ljava/lang/String;
    //   90: invokevirtual 64	java/lang/StringBuilder:append	(Ljava/lang/String;)Ljava/lang/StringBuilder;
    //   93: ldc 86
    //   95: invokevirtual 64	java/lang/StringBuilder:append	(Ljava/lang/String;)Ljava/lang/StringBuilder;
    //   98: invokevirtual 90	java/lang/StringBuilder:toString	()Ljava/lang/String;
    //   101: astore_2
    //   102: aload_0
    //   103: getfield 10	com/tencent/tauth/DownloadFileFromWeiyun$3:this$0	Lcom/tencent/tauth/DownloadFileFromWeiyun;
    //   106: invokestatic 93	com/tencent/tauth/DownloadFileFromWeiyun:access$700	(Lcom/tencent/tauth/DownloadFileFromWeiyun;)Ljava/lang/String;
    //   109: ifnull +46 -> 155
    //   112: aload_0
    //   113: getfield 10	com/tencent/tauth/DownloadFileFromWeiyun$3:this$0	Lcom/tencent/tauth/DownloadFileFromWeiyun;
    //   116: invokestatic 93	com/tencent/tauth/DownloadFileFromWeiyun:access$700	(Lcom/tencent/tauth/DownloadFileFromWeiyun;)Ljava/lang/String;
    //   119: invokevirtual 99	java/lang/String:length	()I
    //   122: ifle +33 -> 155
    //   125: new 57	java/lang/StringBuilder
    //   128: dup
    //   129: invokespecial 58	java/lang/StringBuilder:<init>	()V
    //   132: aload_2
    //   133: invokevirtual 64	java/lang/StringBuilder:append	(Ljava/lang/String;)Ljava/lang/StringBuilder;
    //   136: ldc 101
    //   138: invokevirtual 64	java/lang/StringBuilder:append	(Ljava/lang/String;)Ljava/lang/StringBuilder;
    //   141: aload_0
    //   142: getfield 10	com/tencent/tauth/DownloadFileFromWeiyun$3:this$0	Lcom/tencent/tauth/DownloadFileFromWeiyun;
    //   145: invokestatic 93	com/tencent/tauth/DownloadFileFromWeiyun:access$700	(Lcom/tencent/tauth/DownloadFileFromWeiyun;)Ljava/lang/String;
    //   148: invokevirtual 64	java/lang/StringBuilder:append	(Ljava/lang/String;)Ljava/lang/StringBuilder;
    //   151: invokevirtual 90	java/lang/StringBuilder:toString	()Ljava/lang/String;
    //   154: astore_2
    //   155: new 103	org/apache/http/impl/client/DefaultHttpClient
    //   158: dup
    //   159: aload_1
    //   160: invokespecial 106	org/apache/http/impl/client/DefaultHttpClient:<init>	(Lorg/apache/http/params/HttpParams;)V
    //   163: astore_3
    //   164: aconst_null
    //   165: astore 4
    //   167: new 108	java/io/File
    //   170: dup
    //   171: aload_0
    //   172: getfield 10	com/tencent/tauth/DownloadFileFromWeiyun$3:this$0	Lcom/tencent/tauth/DownloadFileFromWeiyun;
    //   175: invokestatic 111	com/tencent/tauth/DownloadFileFromWeiyun:access$900	(Lcom/tencent/tauth/DownloadFileFromWeiyun;)Ljava/lang/String;
    //   178: aload_0
    //   179: getfield 10	com/tencent/tauth/DownloadFileFromWeiyun$3:this$0	Lcom/tencent/tauth/DownloadFileFromWeiyun;
    //   182: invokestatic 114	com/tencent/tauth/DownloadFileFromWeiyun:access$1000	(Lcom/tencent/tauth/DownloadFileFromWeiyun;)Ljava/lang/String;
    //   185: invokespecial 117	java/io/File:<init>	(Ljava/lang/String;Ljava/lang/String;)V
    //   188: astore 5
    //   190: new 119	java/io/FileOutputStream
    //   193: dup
    //   194: aload 5
    //   196: invokespecial 122	java/io/FileOutputStream:<init>	(Ljava/io/File;)V
    //   199: astore 6
    //   201: ldc 123
    //   203: newarray byte
    //   205: astore 7
    //   207: aload_0
    //   208: getfield 10	com/tencent/tauth/DownloadFileFromWeiyun$3:this$0	Lcom/tencent/tauth/DownloadFileFromWeiyun;
    //   211: invokestatic 127	com/tencent/tauth/DownloadFileFromWeiyun:access$1500	(Lcom/tencent/tauth/DownloadFileFromWeiyun;)Z
    //   214: ifeq +699 -> 913
    //   217: aload_0
    //   218: getfield 10	com/tencent/tauth/DownloadFileFromWeiyun$3:this$0	Lcom/tencent/tauth/DownloadFileFromWeiyun;
    //   221: invokestatic 131	com/tencent/tauth/DownloadFileFromWeiyun:access$1600	(Lcom/tencent/tauth/DownloadFileFromWeiyun;)J
    //   224: ldc2_w 132
    //   227: lcmp
    //   228: ifle +377 -> 605
    //   231: ldc2_w 132
    //   234: lstore 23
    //   236: lload 23
    //   238: lconst_0
    //   239: ladd
    //   240: lstore 25
    //   242: iconst_0
    //   243: istore 27
    //   245: lconst_0
    //   246: lstore 28
    //   248: aconst_null
    //   249: astore 10
    //   251: lload 25
    //   253: lstore 30
    //   255: lload 30
    //   257: aload_0
    //   258: getfield 10	com/tencent/tauth/DownloadFileFromWeiyun$3:this$0	Lcom/tencent/tauth/DownloadFileFromWeiyun;
    //   261: invokestatic 131	com/tencent/tauth/DownloadFileFromWeiyun:access$1600	(Lcom/tencent/tauth/DownloadFileFromWeiyun;)J
    //   264: lcmp
    //   265: ifgt +468 -> 733
    //   268: new 135	org/apache/http/client/methods/HttpGet
    //   271: dup
    //   272: aload_2
    //   273: invokespecial 138	org/apache/http/client/methods/HttpGet:<init>	(Ljava/lang/String;)V
    //   276: astore 32
    //   278: aload 32
    //   280: ldc 140
    //   282: ldc 142
    //   284: invokeinterface 147 3 0
    //   289: aload 32
    //   291: ldc 149
    //   293: aload_0
    //   294: getfield 10	com/tencent/tauth/DownloadFileFromWeiyun$3:this$0	Lcom/tencent/tauth/DownloadFileFromWeiyun;
    //   297: invokestatic 70	com/tencent/tauth/DownloadFileFromWeiyun:access$500	(Lcom/tencent/tauth/DownloadFileFromWeiyun;)Ljava/lang/String;
    //   300: invokeinterface 147 3 0
    //   305: aload 32
    //   307: ldc 151
    //   309: ldc 153
    //   311: invokeinterface 147 3 0
    //   316: aload 32
    //   318: ldc 155
    //   320: new 57	java/lang/StringBuilder
    //   323: dup
    //   324: invokespecial 58	java/lang/StringBuilder:<init>	()V
    //   327: aload_0
    //   328: getfield 10	com/tencent/tauth/DownloadFileFromWeiyun$3:this$0	Lcom/tencent/tauth/DownloadFileFromWeiyun;
    //   331: invokestatic 158	com/tencent/tauth/DownloadFileFromWeiyun:access$200	(Lcom/tencent/tauth/DownloadFileFromWeiyun;)Ljava/lang/String;
    //   334: invokevirtual 64	java/lang/StringBuilder:append	(Ljava/lang/String;)Ljava/lang/StringBuilder;
    //   337: ldc 160
    //   339: invokevirtual 64	java/lang/StringBuilder:append	(Ljava/lang/String;)Ljava/lang/StringBuilder;
    //   342: aload_0
    //   343: getfield 10	com/tencent/tauth/DownloadFileFromWeiyun$3:this$0	Lcom/tencent/tauth/DownloadFileFromWeiyun;
    //   346: invokestatic 163	com/tencent/tauth/DownloadFileFromWeiyun:access$300	(Lcom/tencent/tauth/DownloadFileFromWeiyun;)Ljava/lang/String;
    //   349: invokevirtual 64	java/lang/StringBuilder:append	(Ljava/lang/String;)Ljava/lang/StringBuilder;
    //   352: ldc 165
    //   354: invokevirtual 64	java/lang/StringBuilder:append	(Ljava/lang/String;)Ljava/lang/StringBuilder;
    //   357: invokevirtual 90	java/lang/StringBuilder:toString	()Ljava/lang/String;
    //   360: invokeinterface 147 3 0
    //   365: aload 32
    //   367: ldc 167
    //   369: ldc 169
    //   371: invokeinterface 147 3 0
    //   376: aload 32
    //   378: ldc 171
    //   380: new 57	java/lang/StringBuilder
    //   383: dup
    //   384: invokespecial 58	java/lang/StringBuilder:<init>	()V
    //   387: ldc 173
    //   389: invokevirtual 64	java/lang/StringBuilder:append	(Ljava/lang/String;)Ljava/lang/StringBuilder;
    //   392: lload 28
    //   394: invokevirtual 176	java/lang/StringBuilder:append	(J)Ljava/lang/StringBuilder;
    //   397: ldc 178
    //   399: invokevirtual 64	java/lang/StringBuilder:append	(Ljava/lang/String;)Ljava/lang/StringBuilder;
    //   402: lload 30
    //   404: invokevirtual 176	java/lang/StringBuilder:append	(J)Ljava/lang/StringBuilder;
    //   407: ldc 165
    //   409: invokevirtual 64	java/lang/StringBuilder:append	(Ljava/lang/String;)Ljava/lang/StringBuilder;
    //   412: invokevirtual 90	java/lang/StringBuilder:toString	()Ljava/lang/String;
    //   415: invokeinterface 147 3 0
    //   420: aload_3
    //   421: aload 32
    //   423: invokeinterface 184 2 0
    //   428: astore 41
    //   430: ldc 186
    //   432: new 57	java/lang/StringBuilder
    //   435: dup
    //   436: invokespecial 58	java/lang/StringBuilder:<init>	()V
    //   439: ldc 188
    //   441: invokevirtual 64	java/lang/StringBuilder:append	(Ljava/lang/String;)Ljava/lang/StringBuilder;
    //   444: aload 41
    //   446: invokevirtual 191	java/lang/Object:toString	()Ljava/lang/String;
    //   449: invokevirtual 64	java/lang/StringBuilder:append	(Ljava/lang/String;)Ljava/lang/StringBuilder;
    //   452: invokevirtual 90	java/lang/StringBuilder:toString	()Ljava/lang/String;
    //   455: invokestatic 197	android/util/Log:i	(Ljava/lang/String;Ljava/lang/String;)I
    //   458: pop
    //   459: aload 41
    //   461: invokeinterface 203 1 0
    //   466: invokeinterface 208 1 0
    //   471: istore 43
    //   473: iload 43
    //   475: sipush 200
    //   478: if_icmpeq +11 -> 489
    //   481: iload 43
    //   483: sipush 206
    //   486: if_icmpne +247 -> 733
    //   489: aload 41
    //   491: invokeinterface 212 1 0
    //   496: invokeinterface 218 1 0
    //   501: astore 10
    //   503: aload 10
    //   505: aload 7
    //   507: invokevirtual 224	java/io/InputStream:read	([B)I
    //   510: istore 44
    //   512: iload 44
    //   514: ifle +269 -> 783
    //   517: aload 6
    //   519: aload 7
    //   521: iconst_0
    //   522: iload 44
    //   524: invokevirtual 228	java/io/FileOutputStream:write	([BII)V
    //   527: lload 28
    //   529: iload 44
    //   531: i2l
    //   532: ladd
    //   533: lstore 28
    //   535: goto -32 -> 503
    //   538: astore 45
    //   540: aload 45
    //   542: invokevirtual 231	java/io/FileNotFoundException:printStackTrace	()V
    //   545: aload_0
    //   546: getfield 10	com/tencent/tauth/DownloadFileFromWeiyun$3:this$0	Lcom/tencent/tauth/DownloadFileFromWeiyun;
    //   549: invokestatic 235	com/tencent/tauth/DownloadFileFromWeiyun:access$1400	(Lcom/tencent/tauth/DownloadFileFromWeiyun;)Landroid/os/Handler;
    //   552: invokevirtual 241	android/os/Handler:obtainMessage	()Landroid/os/Message;
    //   555: astore 46
    //   557: aload 46
    //   559: iconst_3
    //   560: putfield 247	android/os/Message:what	I
    //   563: aload 46
    //   565: new 57	java/lang/StringBuilder
    //   568: dup
    //   569: invokespecial 58	java/lang/StringBuilder:<init>	()V
    //   572: aload 45
    //   574: invokevirtual 250	java/io/FileNotFoundException:getMessage	()Ljava/lang/String;
    //   577: invokevirtual 64	java/lang/StringBuilder:append	(Ljava/lang/String;)Ljava/lang/StringBuilder;
    //   580: ldc 165
    //   582: invokevirtual 64	java/lang/StringBuilder:append	(Ljava/lang/String;)Ljava/lang/StringBuilder;
    //   585: invokevirtual 90	java/lang/StringBuilder:toString	()Ljava/lang/String;
    //   588: putfield 254	android/os/Message:obj	Ljava/lang/Object;
    //   591: aload_0
    //   592: getfield 10	com/tencent/tauth/DownloadFileFromWeiyun$3:this$0	Lcom/tencent/tauth/DownloadFileFromWeiyun;
    //   595: invokestatic 235	com/tencent/tauth/DownloadFileFromWeiyun:access$1400	(Lcom/tencent/tauth/DownloadFileFromWeiyun;)Landroid/os/Handler;
    //   598: aload 46
    //   600: invokevirtual 258	android/os/Handler:sendMessage	(Landroid/os/Message;)Z
    //   603: pop
    //   604: return
    //   605: aload_0
    //   606: getfield 10	com/tencent/tauth/DownloadFileFromWeiyun$3:this$0	Lcom/tencent/tauth/DownloadFileFromWeiyun;
    //   609: invokestatic 131	com/tencent/tauth/DownloadFileFromWeiyun:access$1600	(Lcom/tencent/tauth/DownloadFileFromWeiyun;)J
    //   612: lstore 23
    //   614: goto -378 -> 236
    //   617: astore 33
    //   619: iinc 27 1
    //   622: iload 27
    //   624: aload_0
    //   625: getfield 10	com/tencent/tauth/DownloadFileFromWeiyun$3:this$0	Lcom/tencent/tauth/DownloadFileFromWeiyun;
    //   628: invokestatic 261	com/tencent/tauth/DownloadFileFromWeiyun:access$1700	(Lcom/tencent/tauth/DownloadFileFromWeiyun;)I
    //   631: if_icmple +152 -> 783
    //   634: aload 33
    //   636: invokevirtual 262	java/lang/Exception:printStackTrace	()V
    //   639: ldc 186
    //   641: new 57	java/lang/StringBuilder
    //   644: dup
    //   645: invokespecial 58	java/lang/StringBuilder:<init>	()V
    //   648: ldc_w 264
    //   651: invokevirtual 64	java/lang/StringBuilder:append	(Ljava/lang/String;)Ljava/lang/StringBuilder;
    //   654: aload 33
    //   656: invokevirtual 265	java/lang/Exception:getMessage	()Ljava/lang/String;
    //   659: invokevirtual 64	java/lang/StringBuilder:append	(Ljava/lang/String;)Ljava/lang/StringBuilder;
    //   662: ldc 165
    //   664: invokevirtual 64	java/lang/StringBuilder:append	(Ljava/lang/String;)Ljava/lang/StringBuilder;
    //   667: invokevirtual 90	java/lang/StringBuilder:toString	()Ljava/lang/String;
    //   670: invokestatic 268	android/util/Log:e	(Ljava/lang/String;Ljava/lang/String;)I
    //   673: pop
    //   674: aload_0
    //   675: getfield 10	com/tencent/tauth/DownloadFileFromWeiyun$3:this$0	Lcom/tencent/tauth/DownloadFileFromWeiyun;
    //   678: invokestatic 235	com/tencent/tauth/DownloadFileFromWeiyun:access$1400	(Lcom/tencent/tauth/DownloadFileFromWeiyun;)Landroid/os/Handler;
    //   681: invokevirtual 241	android/os/Handler:obtainMessage	()Landroid/os/Message;
    //   684: astore 39
    //   686: aload 39
    //   688: iconst_3
    //   689: putfield 247	android/os/Message:what	I
    //   692: aload 39
    //   694: new 57	java/lang/StringBuilder
    //   697: dup
    //   698: invokespecial 58	java/lang/StringBuilder:<init>	()V
    //   701: aload 33
    //   703: invokevirtual 265	java/lang/Exception:getMessage	()Ljava/lang/String;
    //   706: invokevirtual 64	java/lang/StringBuilder:append	(Ljava/lang/String;)Ljava/lang/StringBuilder;
    //   709: ldc 165
    //   711: invokevirtual 64	java/lang/StringBuilder:append	(Ljava/lang/String;)Ljava/lang/StringBuilder;
    //   714: invokevirtual 90	java/lang/StringBuilder:toString	()Ljava/lang/String;
    //   717: putfield 254	android/os/Message:obj	Ljava/lang/Object;
    //   720: aload_0
    //   721: getfield 10	com/tencent/tauth/DownloadFileFromWeiyun$3:this$0	Lcom/tencent/tauth/DownloadFileFromWeiyun;
    //   724: invokestatic 235	com/tencent/tauth/DownloadFileFromWeiyun:access$1400	(Lcom/tencent/tauth/DownloadFileFromWeiyun;)Landroid/os/Handler;
    //   727: aload 39
    //   729: invokevirtual 258	android/os/Handler:sendMessage	(Landroid/os/Message;)Z
    //   732: pop
    //   733: aload 6
    //   735: invokevirtual 271	java/io/FileOutputStream:close	()V
    //   738: aload 10
    //   740: invokevirtual 272	java/io/InputStream:close	()V
    //   743: aload_0
    //   744: getfield 10	com/tencent/tauth/DownloadFileFromWeiyun$3:this$0	Lcom/tencent/tauth/DownloadFileFromWeiyun;
    //   747: invokestatic 235	com/tencent/tauth/DownloadFileFromWeiyun:access$1400	(Lcom/tencent/tauth/DownloadFileFromWeiyun;)Landroid/os/Handler;
    //   750: invokevirtual 241	android/os/Handler:obtainMessage	()Landroid/os/Message;
    //   753: astore 14
    //   755: aload 14
    //   757: iconst_1
    //   758: putfield 247	android/os/Message:what	I
    //   761: aload 14
    //   763: ldc_w 274
    //   766: putfield 254	android/os/Message:obj	Ljava/lang/Object;
    //   769: aload_0
    //   770: getfield 10	com/tencent/tauth/DownloadFileFromWeiyun$3:this$0	Lcom/tencent/tauth/DownloadFileFromWeiyun;
    //   773: invokestatic 235	com/tencent/tauth/DownloadFileFromWeiyun:access$1400	(Lcom/tencent/tauth/DownloadFileFromWeiyun;)Landroid/os/Handler;
    //   776: aload 14
    //   778: invokevirtual 258	android/os/Handler:sendMessage	(Landroid/os/Message;)Z
    //   781: pop
    //   782: return
    //   783: aload_0
    //   784: getfield 10	com/tencent/tauth/DownloadFileFromWeiyun$3:this$0	Lcom/tencent/tauth/DownloadFileFromWeiyun;
    //   787: invokestatic 131	com/tencent/tauth/DownloadFileFromWeiyun:access$1600	(Lcom/tencent/tauth/DownloadFileFromWeiyun;)J
    //   790: lload 30
    //   792: lsub
    //   793: lconst_0
    //   794: lcmp
    //   795: ifle -62 -> 733
    //   798: aload_0
    //   799: getfield 10	com/tencent/tauth/DownloadFileFromWeiyun$3:this$0	Lcom/tencent/tauth/DownloadFileFromWeiyun;
    //   802: invokestatic 131	com/tencent/tauth/DownloadFileFromWeiyun:access$1600	(Lcom/tencent/tauth/DownloadFileFromWeiyun;)J
    //   805: lload 28
    //   807: lsub
    //   808: ldc2_w 132
    //   811: lcmp
    //   812: ifle +86 -> 898
    //   815: ldc2_w 132
    //   818: lstore 34
    //   820: lload 34
    //   822: lload 28
    //   824: ladd
    //   825: lstore 30
    //   827: aload_0
    //   828: getfield 10	com/tencent/tauth/DownloadFileFromWeiyun$3:this$0	Lcom/tencent/tauth/DownloadFileFromWeiyun;
    //   831: invokestatic 235	com/tencent/tauth/DownloadFileFromWeiyun:access$1400	(Lcom/tencent/tauth/DownloadFileFromWeiyun;)Landroid/os/Handler;
    //   834: invokevirtual 241	android/os/Handler:obtainMessage	()Landroid/os/Message;
    //   837: astore 36
    //   839: aload 36
    //   841: iconst_2
    //   842: putfield 247	android/os/Message:what	I
    //   845: aload 36
    //   847: new 57	java/lang/StringBuilder
    //   850: dup
    //   851: invokespecial 58	java/lang/StringBuilder:<init>	()V
    //   854: ldc2_w 275
    //   857: lload 30
    //   859: lmul
    //   860: aload_0
    //   861: getfield 10	com/tencent/tauth/DownloadFileFromWeiyun$3:this$0	Lcom/tencent/tauth/DownloadFileFromWeiyun;
    //   864: invokestatic 131	com/tencent/tauth/DownloadFileFromWeiyun:access$1600	(Lcom/tencent/tauth/DownloadFileFromWeiyun;)J
    //   867: ldiv
    //   868: invokevirtual 176	java/lang/StringBuilder:append	(J)Ljava/lang/StringBuilder;
    //   871: ldc 165
    //   873: invokevirtual 64	java/lang/StringBuilder:append	(Ljava/lang/String;)Ljava/lang/StringBuilder;
    //   876: invokevirtual 90	java/lang/StringBuilder:toString	()Ljava/lang/String;
    //   879: putfield 254	android/os/Message:obj	Ljava/lang/Object;
    //   882: aload_0
    //   883: getfield 10	com/tencent/tauth/DownloadFileFromWeiyun$3:this$0	Lcom/tencent/tauth/DownloadFileFromWeiyun;
    //   886: invokestatic 235	com/tencent/tauth/DownloadFileFromWeiyun:access$1400	(Lcom/tencent/tauth/DownloadFileFromWeiyun;)Landroid/os/Handler;
    //   889: aload 36
    //   891: invokevirtual 258	android/os/Handler:sendMessage	(Landroid/os/Message;)Z
    //   894: pop
    //   895: goto -640 -> 255
    //   898: aload_0
    //   899: getfield 10	com/tencent/tauth/DownloadFileFromWeiyun$3:this$0	Lcom/tencent/tauth/DownloadFileFromWeiyun;
    //   902: invokestatic 131	com/tencent/tauth/DownloadFileFromWeiyun:access$1600	(Lcom/tencent/tauth/DownloadFileFromWeiyun;)J
    //   905: lload 28
    //   907: lsub
    //   908: lstore 34
    //   910: goto -90 -> 820
    //   913: new 135	org/apache/http/client/methods/HttpGet
    //   916: dup
    //   917: aload_2
    //   918: invokespecial 138	org/apache/http/client/methods/HttpGet:<init>	(Ljava/lang/String;)V
    //   921: astore 8
    //   923: aload 8
    //   925: ldc 140
    //   927: ldc 142
    //   929: invokeinterface 147 3 0
    //   934: aload 8
    //   936: ldc 149
    //   938: aload_0
    //   939: getfield 10	com/tencent/tauth/DownloadFileFromWeiyun$3:this$0	Lcom/tencent/tauth/DownloadFileFromWeiyun;
    //   942: invokestatic 70	com/tencent/tauth/DownloadFileFromWeiyun:access$500	(Lcom/tencent/tauth/DownloadFileFromWeiyun;)Ljava/lang/String;
    //   945: invokeinterface 147 3 0
    //   950: aload 8
    //   952: ldc 151
    //   954: ldc 153
    //   956: invokeinterface 147 3 0
    //   961: aload 8
    //   963: ldc 155
    //   965: new 57	java/lang/StringBuilder
    //   968: dup
    //   969: invokespecial 58	java/lang/StringBuilder:<init>	()V
    //   972: aload_0
    //   973: getfield 10	com/tencent/tauth/DownloadFileFromWeiyun$3:this$0	Lcom/tencent/tauth/DownloadFileFromWeiyun;
    //   976: invokestatic 158	com/tencent/tauth/DownloadFileFromWeiyun:access$200	(Lcom/tencent/tauth/DownloadFileFromWeiyun;)Ljava/lang/String;
    //   979: invokevirtual 64	java/lang/StringBuilder:append	(Ljava/lang/String;)Ljava/lang/StringBuilder;
    //   982: ldc 160
    //   984: invokevirtual 64	java/lang/StringBuilder:append	(Ljava/lang/String;)Ljava/lang/StringBuilder;
    //   987: aload_0
    //   988: getfield 10	com/tencent/tauth/DownloadFileFromWeiyun$3:this$0	Lcom/tencent/tauth/DownloadFileFromWeiyun;
    //   991: invokestatic 163	com/tencent/tauth/DownloadFileFromWeiyun:access$300	(Lcom/tencent/tauth/DownloadFileFromWeiyun;)Ljava/lang/String;
    //   994: invokevirtual 64	java/lang/StringBuilder:append	(Ljava/lang/String;)Ljava/lang/StringBuilder;
    //   997: ldc 165
    //   999: invokevirtual 64	java/lang/StringBuilder:append	(Ljava/lang/String;)Ljava/lang/StringBuilder;
    //   1002: invokevirtual 90	java/lang/StringBuilder:toString	()Ljava/lang/String;
    //   1005: invokeinterface 147 3 0
    //   1010: aload 8
    //   1012: ldc 167
    //   1014: ldc 169
    //   1016: invokeinterface 147 3 0
    //   1021: aload_3
    //   1022: aload 8
    //   1024: invokeinterface 184 2 0
    //   1029: astore 19
    //   1031: ldc 186
    //   1033: new 57	java/lang/StringBuilder
    //   1036: dup
    //   1037: invokespecial 58	java/lang/StringBuilder:<init>	()V
    //   1040: ldc 188
    //   1042: invokevirtual 64	java/lang/StringBuilder:append	(Ljava/lang/String;)Ljava/lang/StringBuilder;
    //   1045: aload 19
    //   1047: invokevirtual 191	java/lang/Object:toString	()Ljava/lang/String;
    //   1050: invokevirtual 64	java/lang/StringBuilder:append	(Ljava/lang/String;)Ljava/lang/StringBuilder;
    //   1053: invokevirtual 90	java/lang/StringBuilder:toString	()Ljava/lang/String;
    //   1056: invokestatic 197	android/util/Log:i	(Ljava/lang/String;Ljava/lang/String;)I
    //   1059: pop
    //   1060: aload 19
    //   1062: invokeinterface 203 1 0
    //   1067: invokeinterface 208 1 0
    //   1072: istore 21
    //   1074: iload 21
    //   1076: sipush 200
    //   1079: if_icmpeq +14 -> 1093
    //   1082: aconst_null
    //   1083: astore 4
    //   1085: iload 21
    //   1087: sipush 206
    //   1090: if_icmpne +163 -> 1253
    //   1093: aload 19
    //   1095: invokeinterface 212 1 0
    //   1100: invokeinterface 218 1 0
    //   1105: astore 4
    //   1107: aload 4
    //   1109: aload 7
    //   1111: invokevirtual 224	java/io/InputStream:read	([B)I
    //   1114: istore 22
    //   1116: iload 22
    //   1118: ifle +135 -> 1253
    //   1121: aload 6
    //   1123: aload 7
    //   1125: iconst_0
    //   1126: iload 22
    //   1128: invokevirtual 228	java/io/FileOutputStream:write	([BII)V
    //   1131: goto -24 -> 1107
    //   1134: astore 9
    //   1136: iconst_1
    //   1137: aload_0
    //   1138: getfield 10	com/tencent/tauth/DownloadFileFromWeiyun$3:this$0	Lcom/tencent/tauth/DownloadFileFromWeiyun;
    //   1141: invokestatic 261	com/tencent/tauth/DownloadFileFromWeiyun:access$1700	(Lcom/tencent/tauth/DownloadFileFromWeiyun;)I
    //   1144: if_icmple +102 -> 1246
    //   1147: aload 9
    //   1149: invokevirtual 262	java/lang/Exception:printStackTrace	()V
    //   1152: ldc 186
    //   1154: new 57	java/lang/StringBuilder
    //   1157: dup
    //   1158: invokespecial 58	java/lang/StringBuilder:<init>	()V
    //   1161: ldc_w 264
    //   1164: invokevirtual 64	java/lang/StringBuilder:append	(Ljava/lang/String;)Ljava/lang/StringBuilder;
    //   1167: aload 9
    //   1169: invokevirtual 265	java/lang/Exception:getMessage	()Ljava/lang/String;
    //   1172: invokevirtual 64	java/lang/StringBuilder:append	(Ljava/lang/String;)Ljava/lang/StringBuilder;
    //   1175: ldc 165
    //   1177: invokevirtual 64	java/lang/StringBuilder:append	(Ljava/lang/String;)Ljava/lang/StringBuilder;
    //   1180: invokevirtual 90	java/lang/StringBuilder:toString	()Ljava/lang/String;
    //   1183: invokestatic 268	android/util/Log:e	(Ljava/lang/String;Ljava/lang/String;)I
    //   1186: pop
    //   1187: aload_0
    //   1188: getfield 10	com/tencent/tauth/DownloadFileFromWeiyun$3:this$0	Lcom/tencent/tauth/DownloadFileFromWeiyun;
    //   1191: invokestatic 235	com/tencent/tauth/DownloadFileFromWeiyun:access$1400	(Lcom/tencent/tauth/DownloadFileFromWeiyun;)Landroid/os/Handler;
    //   1194: invokevirtual 241	android/os/Handler:obtainMessage	()Landroid/os/Message;
    //   1197: astore 17
    //   1199: aload 17
    //   1201: iconst_3
    //   1202: putfield 247	android/os/Message:what	I
    //   1205: aload 17
    //   1207: new 57	java/lang/StringBuilder
    //   1210: dup
    //   1211: invokespecial 58	java/lang/StringBuilder:<init>	()V
    //   1214: aload 9
    //   1216: invokevirtual 265	java/lang/Exception:getMessage	()Ljava/lang/String;
    //   1219: invokevirtual 64	java/lang/StringBuilder:append	(Ljava/lang/String;)Ljava/lang/StringBuilder;
    //   1222: ldc 165
    //   1224: invokevirtual 64	java/lang/StringBuilder:append	(Ljava/lang/String;)Ljava/lang/StringBuilder;
    //   1227: invokevirtual 90	java/lang/StringBuilder:toString	()Ljava/lang/String;
    //   1230: putfield 254	android/os/Message:obj	Ljava/lang/Object;
    //   1233: aload_0
    //   1234: getfield 10	com/tencent/tauth/DownloadFileFromWeiyun$3:this$0	Lcom/tencent/tauth/DownloadFileFromWeiyun;
    //   1237: invokestatic 235	com/tencent/tauth/DownloadFileFromWeiyun:access$1400	(Lcom/tencent/tauth/DownloadFileFromWeiyun;)Landroid/os/Handler;
    //   1240: aload 17
    //   1242: invokevirtual 258	android/os/Handler:sendMessage	(Landroid/os/Message;)Z
    //   1245: pop
    //   1246: aload 4
    //   1248: astore 10
    //   1250: goto -517 -> 733
    //   1253: aload 4
    //   1255: astore 10
    //   1257: goto -524 -> 733
    //   1260: astore 11
    //   1262: aload 11
    //   1264: invokevirtual 277	java/io/IOException:printStackTrace	()V
    //   1267: aload_0
    //   1268: getfield 10	com/tencent/tauth/DownloadFileFromWeiyun$3:this$0	Lcom/tencent/tauth/DownloadFileFromWeiyun;
    //   1271: invokestatic 235	com/tencent/tauth/DownloadFileFromWeiyun:access$1400	(Lcom/tencent/tauth/DownloadFileFromWeiyun;)Landroid/os/Handler;
    //   1274: invokevirtual 241	android/os/Handler:obtainMessage	()Landroid/os/Message;
    //   1277: astore 12
    //   1279: aload 12
    //   1281: iconst_3
    //   1282: putfield 247	android/os/Message:what	I
    //   1285: aload 12
    //   1287: new 57	java/lang/StringBuilder
    //   1290: dup
    //   1291: invokespecial 58	java/lang/StringBuilder:<init>	()V
    //   1294: aload 11
    //   1296: invokevirtual 278	java/io/IOException:getMessage	()Ljava/lang/String;
    //   1299: invokevirtual 64	java/lang/StringBuilder:append	(Ljava/lang/String;)Ljava/lang/StringBuilder;
    //   1302: ldc 165
    //   1304: invokevirtual 64	java/lang/StringBuilder:append	(Ljava/lang/String;)Ljava/lang/StringBuilder;
    //   1307: invokevirtual 90	java/lang/StringBuilder:toString	()Ljava/lang/String;
    //   1310: putfield 254	android/os/Message:obj	Ljava/lang/Object;
    //   1313: aload_0
    //   1314: getfield 10	com/tencent/tauth/DownloadFileFromWeiyun$3:this$0	Lcom/tencent/tauth/DownloadFileFromWeiyun;
    //   1317: invokestatic 235	com/tencent/tauth/DownloadFileFromWeiyun:access$1400	(Lcom/tencent/tauth/DownloadFileFromWeiyun;)Landroid/os/Handler;
    //   1320: aload 12
    //   1322: invokevirtual 258	android/os/Handler:sendMessage	(Landroid/os/Message;)Z
    //   1325: pop
    //   1326: return
    //
    // Exception table:
    //   from	to	target	type
    //   190	201	538	java/io/FileNotFoundException
    //   420	473	617	java/lang/Exception
    //   489	503	617	java/lang/Exception
    //   503	512	617	java/lang/Exception
    //   517	527	617	java/lang/Exception
    //   1021	1074	1134	java/lang/Exception
    //   1093	1107	1134	java/lang/Exception
    //   1107	1116	1134	java/lang/Exception
    //   1121	1131	1134	java/lang/Exception
    //   733	743	1260	java/io/IOException
  }
}

/* Location:           C:\9exce\android\pj\kaixin_android_3.9.9_034_kaixin001\classes_dex2jar.jar
 * Qualified Name:     com.tencent.tauth.DownloadFileFromWeiyun.3
 * JD-Core Version:    0.6.0
 */